avrami/__init__.py
avrami/file_load.py
avrami/functions.py
avrami/log_functions.py
avrami/main.py
avrami/plots.py
avrami/setup.py
avrami-1.1.dist-info/METADATA
avrami-1.1.dist-info/WHEEL
avrami-1.1.dist-info/entry_points.txt
avrami-1.1.dist-info/top_level.txt
avrami-1.1.dist-info/RECORD
